sectxt/__init__.py
sectxt-0.9.7.dist-info/LICENCE
sectxt-0.9.7.dist-info/METADATA
sectxt-0.9.7.dist-info/WHEEL
sectxt-0.9.7.dist-info/top_level.txt
sectxt-0.9.7.dist-info/zip-safe
sectxt-0.9.7.dist-info/RECORD
