Metadata-Version: 2.1
Name: sectxt
Version: 0.9.7
Summary: security.txt parser and validator
Author: DigitalTrustCenter
Author-email: algemeen@digitaltrustcenter.nl
License: EUPL-1.2
Platform: any
Classifier: Development Status :: 3 - Alpha
Classifier: Intended Audience :: Developers
Classifier: License :: OSI Approved :: European Union Public Licence 1.2 (EUPL 1.2)
Classifier: Operating System :: OS Independent
Classifier: Programming Language :: Python :: 3
Classifier: Programming Language :: Python :: 3.7
Classifier: Programming Language :: Python :: 3.8
Classifier: Programming Language :: Python :: 3.9
Classifier: Programming Language :: Python :: 3.10
Classifier: Topic :: Software Development
Classifier: Topic :: Software Development :: Libraries
Classifier: Topic :: Software Development :: Libraries :: Python Modules
Requires-Python: >=3.7
License-File: LICENCE
Requires-Dist: requests>=2.32.3
Requires-Dist: python-dateutil>=2.9.0.post0
Requires-Dist: langcodes>=3.5.0
Requires-Dist: pytest>=8.3.4
Requires-Dist: requests-mock>=1.12.1
Requires-Dist: validators>=0.34.0
Requires-Dist: PGPy-dtc>=0.1.1
